{"/_not-found/page":"app/_not-found/page.js","/admin/page":"app/admin/page.js","/douban/page":"app/douban/page.js","/page":"app/page.js","/play/page":"app/play/page.js","/login/page":"app/login/page.js","/search/page":"app/search/page.js","/warning/page":"app/warning/page.js","/api/admin/reset/route":"app/api/admin/reset/route.js","/api/admin/user/route":"app/api/admin/user/route.js","/api/admin/site/route":"app/api/admin/site/route.js","/api/admin/config/route":"app/api/admin/config/route.js","/api/detail/route":"app/api/detail/route.js","/api/change-password/route":"app/api/change-password/route.js","/api/admin/source/route":"app/api/admin/source/route.js","/api/douban/categories/route":"app/api/douban/categories/route.js","/api/cron/route":"app/api/cron/route.js","/api/image-proxy/route":"app/api/image-proxy/route.js","/api/logout/route":"app/api/logout/route.js","/api/search/resources/route":"app/api/search/resources/route.js","/api/douban/route":"app/api/douban/route.js","/api/search/route":"app/api/search/route.js","/api/favorites/route":"app/api/favorites/route.js","/api/playrecords/route":"app/api/playrecords/route.js","/api/server-config/route":"app/api/server-config/route.js","/api/login/route":"app/api/login/route.js","/api/register/route":"app/api/register/route.js","/api/search/one/route":"app/api/search/one/route.js","/api/searchhistory/route":"app/api/searchhistory/route.js"}